rl_envs_forge/__init__.py
rl_envs_forge/envs/__init__.py
rl_envs_forge/envs/acml/README.MD
rl_envs_forge/envs/acml/__init__.py
rl_envs_forge/envs/acml/car_rental/__init__.py
rl_envs_forge/envs/acml/car_rental/car_rental.py
rl_envs_forge/envs/acml/gambler_problem/__init__.py
rl_envs_forge/envs/acml/gambler_problem/gambler_problem.py
rl_envs_forge/envs/common/__init__.py
rl_envs_forge/envs/common/grid_functions.py
rl_envs_forge/envs/grid_world/README.md
rl_envs_forge/envs/grid_world/__init__.py
rl_envs_forge/envs/grid_world/grid_world.py
rl_envs_forge/envs/inverted_pendulum/README.md
rl_envs_forge/envs/inverted_pendulum/__init__.py
rl_envs_forge/envs/inverted_pendulum/cart_pole/README.md
rl_envs_forge/envs/inverted_pendulum/cart_pole/__init__.py
rl_envs_forge/envs/inverted_pendulum/cart_pole/cart_pole.py
rl_envs_forge/envs/inverted_pendulum/pendulum_disk/README.md
rl_envs_forge/envs/inverted_pendulum/pendulum_disk/__init__.py
rl_envs_forge/envs/inverted_pendulum/pendulum_disk/pendulum_disk.py
rl_envs_forge/envs/k_armed_bandit/README.md
rl_envs_forge/envs/k_armed_bandit/__init__.py
rl_envs_forge/envs/k_armed_bandit/k_armed_bandit.py
rl_envs_forge/envs/labyrinth/README.md
rl_envs_forge/envs/labyrinth/__init__.py
rl_envs_forge/envs/labyrinth/constants.py
rl_envs_forge/envs/labyrinth/display/README.md
rl_envs_forge/envs/labyrinth/display/__init__.py
rl_envs_forge/envs/labyrinth/display/display.py
rl_envs_forge/envs/labyrinth/display/player.py
rl_envs_forge/envs/labyrinth/display/sprites/flag.png
rl_envs_forge/envs/labyrinth/display/sprites/player.png
rl_envs_forge/envs/labyrinth/entities/README.md
rl_envs_forge/envs/labyrinth/entities/__init__.py
rl_envs_forge/envs/labyrinth/entities/player.py
rl_envs_forge/envs/labyrinth/labyrinth.py
rl_envs_forge/envs/labyrinth/maze/README.md
rl_envs_forge/envs/labyrinth/maze/__init__.py
rl_envs_forge/envs/labyrinth/maze/corridor.py
rl_envs_forge/envs/labyrinth/maze/maze.py
rl_envs_forge/envs/labyrinth/maze/room.py
rl_envs_forge-5.18.3.dist-info/METADATA
rl_envs_forge-5.18.3.dist-info/WHEEL
rl_envs_forge-5.18.3.dist-info/licenses/LICENSE
rl_envs_forge-5.18.3.dist-info/RECORD
