Metadata-Version: 2.4
Name: rl-envs-forge
Version: 5.18.3
Summary: Environments for reinforcement learning
License: MIT
License-File: LICENSE
Author: mariusdgm
Author-email: marius.dragomir.dgm@gmail.com
Requires-Python: >=3.10,<4.0
Classifier: License :: OSI Approved :: MIT License
Classifier: Programming Language :: Python :: 3
Classifier: Programming Language :: Python :: 3.10
Classifier: Programming Language :: Python :: 3.11
Classifier: Programming Language :: Python :: 3.12
Classifier: Programming Language :: Python :: 3.13
Classifier: Programming Language :: Python :: 3.14
Requires-Dist: graphviz (>=0.20.1,<0.21.0)
Requires-Dist: gymnasium (>=0.29.1,<0.30.0)
Requires-Dist: networkx (>=3.3,<4.0)
Requires-Dist: numpy (>=1.24.1,<2.0.0)
Requires-Dist: pygame (>=2.5.1,<3.0.0)
Requires-Dist: scipy (>=1.11.2,<2.0.0)
Requires-Dist: seaborn (>=0.13.0,<0.14.0)
Requires-Dist: setuptools (>=68.0.0,<69.0.0)
Requires-Dist: sphinx (>=7.2.6,<8.0.0)
Requires-Dist: sphinx-rtd-theme (>=1.3.0,<2.0.0)
Requires-Dist: sphinxcontrib-napoleon (>=0.7,<0.8)
Requires-Dist: toml (>=0.10.2,<0.11.0)
